model_w/preset/django/__init__.py
model_w/preset/django/drf.py
model_w/preset/django/env_helper/__init__.py
model_w/preset/django/env_helper/management/__init__.py
model_w/preset/django/env_helper/management/commands/__init__.py
model_w/preset/django/env_helper/management/commands/list_used_env_vars.py
model_w/preset/django/py.typed
modelw_preset_django-2026.1.0.dist-info/METADATA
modelw_preset_django-2026.1.0.dist-info/WHEEL
modelw_preset_django-2026.1.0.dist-info/licenses/LICENSE
modelw_preset_django-2026.1.0.dist-info/RECORD
